pyrequisites/__init__.py
pyrequisites/_create_empty_dict.py
pyrequisites/_flexible_multilevel_mkdir.py
pyrequisites/_get_parent_directory.py
pyrequisites-0.0.2.dist-info/LICENSE
pyrequisites-0.0.2.dist-info/METADATA
pyrequisites-0.0.2.dist-info/WHEEL
pyrequisites-0.0.2.dist-info/top_level.txt
pyrequisites-0.0.2.dist-info/RECORD
